torchcor/__init__.py
torchcor/device.py
torchcor/core/__init__.py
torchcor/core/assemble.py
torchcor/core/boundary.py
torchcor/core/conductivity.py
torchcor/core/mesh.py
torchcor/core/preconditioner.py
torchcor/core/reorder.py
torchcor/core/solver.py
torchcor/core/stimulation.py
torchcor/core/utils.py
torchcor/core/visualize.py
torchcor/electrodes/electrodes_define.py
torchcor/electrodes/findapexbase.py
torchcor/electrodes/geometrical.py
torchcor/electrodes/meshIO.py
torchcor/ionic/AlievPanfilov.py
torchcor/ionic/CourtemancheRamirezNattel.py
torchcor/ionic/MitchellSchaeffer.py
torchcor/ionic/ModifiedMS2v.py
torchcor/ionic/TenTusscherPanfilov.py
torchcor/ionic/__init__.py
torchcor/ionic/base.py
torchcor/ionic/cellml/__init__.py
torchcor/ionic/cellml/courtemanche_ramirez_nattel_1998.py
torchcor/ionic/cellml/mitchell_schaeffer_2003.py
torchcor/ionic/cellml/single_cell_model.py
torchcor/ionic/cellml/ten_tusscher_model_2006_IK1Ko_endo_units.py
torchcor/signalanalysis/__init__.py
torchcor/signalanalysis/io/__init__.py
torchcor/signalanalysis/io/filelike.py
torchcor/signalanalysis/io/igb.py
torchcor/signalanalysis/signalanalysis/__init__.py
torchcor/signalanalysis/signalanalysis/ecg_QS.py
torchcor/signalanalysis/signalanalysis/egm.py
torchcor/signalanalysis/signalanalysis/general.py
torchcor/signalanalysis/signalanalysis/vcg_QS.py
torchcor/signalanalysis/signalplot/__init__.py
torchcor/signalanalysis/signalplot/ecg.py
torchcor/signalanalysis/signalplot/egm.py
torchcor/signalanalysis/signalplot/general.py
torchcor/signalanalysis/signalplot/vcg.py
torchcor/signalanalysis/tools/__init__.py
torchcor/signalanalysis/tools/maths.py
torchcor/signalanalysis/tools/plotting.py
torchcor/signalanalysis/tools/python.py
torchcor/simulator/__init__.py
torchcor/simulator/atrium.py
torchcor/simulator/atrium_hpc.py
torchcor/simulator/info.py
torchcor/simulator/monodomain.py
torchcor/simulator/test.py
torchcor/simulator/ventricle.py
torchcor/simulator/ventricle_hpc.py
torchcor-0.3.1.dist-info/licenses/LICENSE
torchcor-0.3.1.dist-info/METADATA
torchcor-0.3.1.dist-info/WHEEL
torchcor-0.3.1.dist-info/top_level.txt
torchcor-0.3.1.dist-info/RECORD
