Metadata-Version: 2.4
Name: torchcor
Version: 0.3.1
Summary: High-Performance Large-Scale Cardic Electrophysiology Simulations on GPUs
Author-email: Bei Zhou <bei.zhou@imperial.ac.uk>
Requires-Python: >=3.10
License-File: LICENSE
Requires-Dist: torch
Requires-Dist: matplotlib
Requires-Dist: numpy
Requires-Dist: pygmsh
Requires-Dist: nvidia-ml-py
Requires-Dist: pyvista
Requires-Dist: scipy
Requires-Dist: wfdb
Requires-Dist: seaborn
Requires-Dist: scikit-learn
Requires-Dist: pandas
Dynamic: license-file
